LICENSE
asyncflow/__init__.py
asyncflow/analysis/__init__.py
asyncflow/builder/asyncflow_builder.py
asyncflow/components/__init__.py
asyncflow/config/constants.py
asyncflow/config/plot_constants.py
asyncflow/enums/__init__.py
asyncflow/metrics/analyzer.py
asyncflow/metrics/client.py
asyncflow/metrics/collector.py
asyncflow/metrics/edge.py
asyncflow/metrics/server.py
asyncflow/py.typed
asyncflow/resources/registry.py
asyncflow/resources/server_containers.py
asyncflow/runtime/actors/client.py
asyncflow/runtime/actors/edge.py
asyncflow/runtime/actors/load_balancer.py
asyncflow/runtime/actors/routing/lb_algorithms.py
asyncflow/runtime/actors/rqs_generator.py
asyncflow/runtime/actors/server.py
asyncflow/runtime/events/injection.py
asyncflow/runtime/rqs_state.py
asyncflow/runtime/simulation_runner.py
asyncflow/samplers/common_helpers.py
asyncflow/samplers/gaussian_poisson.py
asyncflow/samplers/poisson_poisson.py
asyncflow/schemas/common/__init__.py
asyncflow/schemas/common/random_variables.py
asyncflow/schemas/events/injection.py
asyncflow/schemas/payload.py
asyncflow/schemas/settings/simulation.py
asyncflow/schemas/topology/edges.py
asyncflow/schemas/topology/endpoint.py
asyncflow/schemas/topology/graph.py
asyncflow/schemas/topology/nodes.py
asyncflow/schemas/workload/rqs_generator.py
asyncflow/settings/__init__.py
asyncflow/workload/__init__.py
asyncflow_sim-0.1.1.dist-info/LICENSE
asyncflow_sim-0.1.1.dist-info/METADATA
asyncflow_sim-0.1.1.dist-info/WHEEL
asyncflow_sim-0.1.1.dist-info/RECORD
