Metadata-Version: 2.1
Name: asyncflow-sim
Version: 0.1.1
Summary: Digital-twin simulator for distributed async systems. Build what-if scenarios and quantify capacity, latency and throughput offline, before you deploy.
Home-page: https://github.com/AsyncFlow-Sim/AsyncFlow
License: MIT
Keywords: simulation,simpy,asyncio,capacity-planning,performance,fastapi,uvicorn,distributed-systems,queuing-theory
Author: Gioele Botta
Requires-Python: >=3.12,<4.0
Classifier: Development Status :: 3 - Alpha
Classifier: Intended Audience :: Developers
Classifier: Intended Audience :: Science/Research
Classifier: License :: OSI Approved :: MIT License
Classifier: Operating System :: OS Independent
Classifier: Programming Language :: Python :: 3
Classifier: Programming Language :: Python :: 3.12
Classifier: Topic :: Software Development :: Testing
Classifier: Topic :: System :: Benchmark
Classifier: Topic :: System :: Distributed Computing
Classifier: Typing :: Typed
Requires-Dist: matplotlib (>=3.10.3,<4.0.0)
Requires-Dist: numpy (>=2.3.1,<3.0.0)
Requires-Dist: pydantic-settings (>=2.10.1,<3.0.0)
Requires-Dist: pydantic[email] (>=2.11.7,<3.0.0)
Requires-Dist: pyyaml (>=6.0.2,<7.0.0)
Requires-Dist: simpy (>=4.1.1,<5.0.0)
Project-URL: Documentation, https://github.com/AsyncFlow-Sim/AsyncFlow/tree/main/docs
Project-URL: Repository, https://github.com/AsyncFlow-Sim/AsyncFlow
